<?xml version="1.0" encoding="UTF-8"?><record_update>
    <sys_choice action="INSERT_OR_UPDATE" field="experience" table="x_1606613_gym_ma_0_gym_users" version="3">
        <sys_choice_set action="INSERT_OR_UPDATE">
            <element>experience</element>
            <name>x_1606613_gym_ma_0_gym_users</name>
            <sys_class_name>sys_choice_set</sys_class_name>
            <sys_created_by>admin</sys_created_by>
            <sys_created_on>2025-08-30 18:44:39</sys_created_on>
            <sys_mod_count>0</sys_mod_count>
            <sys_name>experience</sys_name>
            <sys_package display_value="GYM Management Application" source="x_1606613_gym_ma_0">e737c57383632210ed9bfe55eeaad3ee</sys_package>
            <sys_policy/>
            <sys_scope display_value="GYM Management Application">e737c57383632210ed9bfe55eeaad3ee</sys_scope>
            <sys_update_name>sys_choice_x_1606613_gym_ma_0_gym_users_experience</sys_update_name>
            <sys_updated_by>admin</sys_updated_by>
            <sys_updated_on>2025-08-30 18:44:39</sys_updated_on>
        </sys_choice_set>
        <sys_choice action="INSERT_OR_UPDATE">
            <dependent_value/>
            <element>experience</element>
            <hint/>
            <inactive>false</inactive>
            <label>1</label>
            <language>en</language>
            <name>x_1606613_gym_ma_0_gym_users</name>
            <sequence>0</sequence>
            <synonyms/>
            <sys_created_by>admin</sys_created_by>
            <sys_created_on>2025-08-30 18:44:39</sys_created_on>
            <sys_domain>global</sys_domain>
            <sys_domain_path>/</sys_domain_path>
            <sys_mod_count>0</sys_mod_count>
            <sys_updated_by>admin</sys_updated_by>
            <sys_updated_on>2025-08-30 18:44:39</sys_updated_on>
            <value>1</value>
        </sys_choice>
        <sys_choice action="INSERT_OR_UPDATE">
            <dependent_value/>
            <element>experience</element>
            <hint/>
            <inactive>false</inactive>
            <label>2</label>
            <language>en</language>
            <name>x_1606613_gym_ma_0_gym_users</name>
            <sequence>1</sequence>
            <synonyms/>
            <sys_created_by>admin</sys_created_by>
            <sys_created_on>2025-08-30 18:44:39</sys_created_on>
            <sys_domain>global</sys_domain>
            <sys_domain_path>/</sys_domain_path>
            <sys_mod_count>0</sys_mod_count>
            <sys_updated_by>admin</sys_updated_by>
            <sys_updated_on>2025-08-30 18:44:39</sys_updated_on>
            <value>2</value>
        </sys_choice>
        <sys_choice action="INSERT_OR_UPDATE">
            <dependent_value/>
            <element>experience</element>
            <hint/>
            <inactive>false</inactive>
            <label>3</label>
            <language>en</language>
            <name>x_1606613_gym_ma_0_gym_users</name>
            <sequence>2</sequence>
            <synonyms/>
            <sys_created_by>admin</sys_created_by>
            <sys_created_on>2025-08-30 18:44:39</sys_created_on>
            <sys_domain>global</sys_domain>
            <sys_domain_path>/</sys_domain_path>
            <sys_mod_count>0</sys_mod_count>
            <sys_updated_by>admin</sys_updated_by>
            <sys_updated_on>2025-08-30 18:44:39</sys_updated_on>
            <value>3</value>
        </sys_choice>
        <sys_choice action="INSERT_OR_UPDATE">
            <dependent_value/>
            <element>experience</element>
            <hint/>
            <inactive>false</inactive>
            <label>4</label>
            <language>en</language>
            <name>x_1606613_gym_ma_0_gym_users</name>
            <sequence>3</sequence>
            <synonyms/>
            <sys_created_by>admin</sys_created_by>
            <sys_created_on>2025-08-30 18:44:39</sys_created_on>
            <sys_domain>global</sys_domain>
            <sys_domain_path>/</sys_domain_path>
            <sys_mod_count>0</sys_mod_count>
            <sys_updated_by>admin</sys_updated_by>
            <sys_updated_on>2025-08-30 18:44:39</sys_updated_on>
            <value>4</value>
        </sys_choice>
        <sys_choice action="INSERT_OR_UPDATE">
            <dependent_value/>
            <element>experience</element>
            <hint/>
            <inactive>false</inactive>
            <label>5</label>
            <language>en</language>
            <name>x_1606613_gym_ma_0_gym_users</name>
            <sequence>4</sequence>
            <synonyms/>
            <sys_created_by>admin</sys_created_by>
            <sys_created_on>2025-08-30 18:44:39</sys_created_on>
            <sys_domain>global</sys_domain>
            <sys_domain_path>/</sys_domain_path>
            <sys_mod_count>0</sys_mod_count>
            <sys_updated_by>admin</sys_updated_by>
            <sys_updated_on>2025-08-30 18:44:39</sys_updated_on>
            <value>5</value>
        </sys_choice>
        <sys_choice action="INSERT_OR_UPDATE">
            <dependent_value/>
            <element>experience</element>
            <hint/>
            <inactive>false</inactive>
            <label>6</label>
            <language>en</language>
            <name>x_1606613_gym_ma_0_gym_users</name>
            <sequence>5</sequence>
            <synonyms/>
            <sys_created_by>admin</sys_created_by>
            <sys_created_on>2025-08-30 18:44:39</sys_created_on>
            <sys_domain>global</sys_domain>
            <sys_domain_path>/</sys_domain_path>
            <sys_mod_count>0</sys_mod_count>
            <sys_updated_by>admin</sys_updated_by>
            <sys_updated_on>2025-08-30 18:44:39</sys_updated_on>
            <value>6</value>
        </sys_choice>
        <sys_choice action="INSERT_OR_UPDATE">
            <dependent_value/>
            <element>experience</element>
            <hint/>
            <inactive>false</inactive>
            <label>7</label>
            <language>en</language>
            <name>x_1606613_gym_ma_0_gym_users</name>
            <sequence>6</sequence>
            <synonyms/>
            <sys_created_by>admin</sys_created_by>
            <sys_created_on>2025-08-30 18:44:39</sys_created_on>
            <sys_domain>global</sys_domain>
            <sys_domain_path>/</sys_domain_path>
            <sys_mod_count>0</sys_mod_count>
            <sys_updated_by>admin</sys_updated_by>
            <sys_updated_on>2025-08-30 18:44:39</sys_updated_on>
            <value>7</value>
        </sys_choice>
        <sys_choice action="INSERT_OR_UPDATE">
            <dependent_value/>
            <element>experience</element>
            <hint/>
            <inactive>false</inactive>
            <label>8</label>
            <language>en</language>
            <name>x_1606613_gym_ma_0_gym_users</name>
            <sequence>7</sequence>
            <synonyms/>
            <sys_created_by>admin</sys_created_by>
            <sys_created_on>2025-08-30 18:44:39</sys_created_on>
            <sys_domain>global</sys_domain>
            <sys_domain_path>/</sys_domain_path>
            <sys_mod_count>0</sys_mod_count>
            <sys_updated_by>admin</sys_updated_by>
            <sys_updated_on>2025-08-30 18:44:39</sys_updated_on>
            <value>8</value>
        </sys_choice>
        <sys_choice action="INSERT_OR_UPDATE">
            <dependent_value/>
            <element>experience</element>
            <hint/>
            <inactive>false</inactive>
            <label>9</label>
            <language>en</language>
            <name>x_1606613_gym_ma_0_gym_users</name>
            <sequence>8</sequence>
            <synonyms/>
            <sys_created_by>admin</sys_created_by>
            <sys_created_on>2025-08-30 18:44:39</sys_created_on>
            <sys_domain>global</sys_domain>
            <sys_domain_path>/</sys_domain_path>
            <sys_mod_count>0</sys_mod_count>
            <sys_updated_by>admin</sys_updated_by>
            <sys_updated_on>2025-08-30 18:44:39</sys_updated_on>
            <value>9</value>
        </sys_choice>
        <sys_choice action="INSERT_OR_UPDATE">
            <dependent_value/>
            <element>experience</element>
            <hint/>
            <inactive>false</inactive>
            <label>10</label>
            <language>en</language>
            <name>x_1606613_gym_ma_0_gym_users</name>
            <sequence>9</sequence>
            <synonyms/>
            <sys_created_by>admin</sys_created_by>
            <sys_created_on>2025-08-30 18:44:39</sys_created_on>
            <sys_domain>global</sys_domain>
            <sys_domain_path>/</sys_domain_path>
            <sys_mod_count>0</sys_mod_count>
            <sys_updated_by>admin</sys_updated_by>
            <sys_updated_on>2025-08-30 18:44:39</sys_updated_on>
            <value>10</value>
        </sys_choice>
        <sys_choice action="INSERT_OR_UPDATE">
            <dependent_value/>
            <element>experience</element>
            <hint/>
            <inactive>false</inactive>
            <label>11</label>
            <language>en</language>
            <name>x_1606613_gym_ma_0_gym_users</name>
            <sequence>10</sequence>
            <synonyms/>
            <sys_created_by>admin</sys_created_by>
            <sys_created_on>2025-08-30 18:44:39</sys_created_on>
            <sys_domain>global</sys_domain>
            <sys_domain_path>/</sys_domain_path>
            <sys_mod_count>0</sys_mod_count>
            <sys_updated_by>admin</sys_updated_by>
            <sys_updated_on>2025-08-30 18:44:39</sys_updated_on>
            <value>11</value>
        </sys_choice>
    </sys_choice>
</record_update>
